{
  "palaces": {
    "save": {
      "type": "palace",
      "rooms": {
        "lobby": {
          "type": "room",
          "contents": {}
        },
        "fields": {
          "type": "room",
          "contents": {}
        }
      },
      "wings": {
        "scum": {
          "type": "wing",
          "rooms": {
            "sewer": {
              "type": "room",
              "contents": {
                "conga": {
                  "type": "box",
                  "value": "arrrrrriba",
                  "value_type": "string"
                },
                "sea quest": {
                  "type": "chain",
                  "value_type": "number",
                  "links": [
                    {
                      "value": 1
                    },
                    {
                      "value": 1
                    }
                  ]
                },
                "tennis": {
                  "type": "ball",
                  "radius": {
                    "type": "box",
                    "value": 10,
                    "value_type": "number"
                  }
                }
              }
            }
          }
        }
      },
      "types": {
        "circle": {
          "type": "type_def",
          "parent": "bag",
          "radius": {
            "type": "box",
            "value": null,
            "value_type": "number"
          },
          "area": {
            "type": "device",
            "input": {
              "name": "input",
              "value_type": null,
              "value": null
            },
            "process": [
              {
                "type": "command",
                "operator": "return",
                "arguments": [
                  {
                    "type": "command",
                    "operator": "multiply",
                    "arguments": [
                      {
                        "type": "number",
                        "value": 3.14
                      },
                      {
                        "type": "command",
                        "operator": "squared",
                        "arguments": [
                          {
                            "type": "reference",
                            "name": "radius"
                          }
                        ]
                      }
                    ]
                  }
                ]
              }
            ],
            "pattern": {
              "type": "pattern",
              "chain": {
                "type": "chain",
                "value_type": "string",
                "links": [
                  {
                    "value": "area"
                  },
                  {
                    "value": "of?"
                  },
                  {
                    "value": "<parent>"
                  }
                ]
              },
              "comment": ""
            }
          }
        },
        "ball": {
          "type": "type_def",
          "parent": "circle"
        }
      }
    }
  }
}